mantas_currency_converter/__init__.py
mantas_currency_converter/converter.py
mantas_currency_converter/main.py
mantas_currency_converter-0.1.2.dist-info/METADATA
mantas_currency_converter-0.1.2.dist-info/WHEEL
mantas_currency_converter-0.1.2.dist-info/top_level.txt
mantas_currency_converter-0.1.2.dist-info/RECORD
