Metadata-Version: 2.1
Name: mantas-currency-converter
Version: 0.1.2
Author: Meskenaz
Requires-Python: >=3.9
Requires-Dist: CurrencyConverter ==0.17.34
